{
  "generated": "2026-06-04T07:45:00.000Z",
  "gw": 38,
  "squad_count": 15,
  "universe_count": 149,
  "squad_features": [
    {
      "id": 1,
      "web_name": "Verbruggen",
      "team": "BHA",
      "position": "GK",
      "now_cost": 4.6,
      "xpts_next": 0,
      "captain_xpts": 0,
      "fdr": 3,
      "ownership": null,
      "news": "",
      "news_status": "AVAILABLE",
      "price_change_flag": "none",
      "is_starting": true,
      "is_captain": false,
      "is_vice": false
    },
    {
      "id": 2,
      "web_name": "Hill",
      "team": "BOU",
      "position": "DEF",
      "now_cost": 4.2,
      "xpts_next": 0,
      "captain_xpts": 0,
      "fdr": 3,
      "ownership": null,
      "news": "",
      "news_status": "AVAILABLE",
      "price_change_flag": "none",
      "is_starting": true,
      "is_captain": false,
      "is_vice": false
    },
    {
      "id": 3,
      "web_name": "Thiaw",
      "team": "NEW",
      "position": "DEF",
      "now_cost": 4.9,
      "xpts_next": 0,
      "captain_xpts": 0,
      "fdr": 3,
      "ownership": null,
      "news": "",
      "news_status": "AVAILABLE",
      "price_change_flag": "none",
      "is_starting": true,
      "is_captain": false,
      "is_vice": false
    },
    {
      "id": 4,
      "web_name": "Gabriel",
      "team": "ARS",
      "position": "DEF",
      "now_cost": 7.3,
      "xpts_next": 0,
      "captain_xpts": 0,
      "fdr": 3,
      "ownership": null,
      "news": "",
      "news_status": "AVAILABLE",
      "price_change_flag": "none",
      "is_starting": true,
      "is_captain": false,
      "is_vice": true
    },
    {
      "id": 5,
      "web_name": "B.Fernandes",
      "team": "MUN",
      "position": "MID",
      "now_cost": 10.4,
      "xpts_next": 0,
      "captain_xpts": 0,
      "fdr": 3,
      "ownership": null,
      "news": "",
      "news_status": "AVAILABLE",
      "price_change_flag": "none",
      "is_starting": true,
      "is_captain": false,
      "is_vice": false
    },
    {
      "id": 6,
      "web_name": "Rice",
      "team": "ARS",
      "position": "MID",
      "now_cost": 7.2,
      "xpts_next": 0,
      "captain_xpts": 0,
      "fdr": 3,
      "ownership": null,
      "news": "",
      "news_status": "AVAILABLE",
      "price_change_flag": "none",
      "is_starting": true,
      "is_captain": false,
      "is_vice": false
    },
    {
      "id": 7,
      "web_name": "Anderson",
      "team": "NFO",
      "position": "MID",
      "now_cost": 5.7,
      "xpts_next": 0,
      "captain_xpts": 0,
      "fdr": 3,
      "ownership": null,
      "news": "",
      "news_status": "AVAILABLE",
      "price_change_flag": "none",
      "is_starting": true,
      "is_captain": false,
      "is_vice": false
    },
    {
      "id": 8,
      "web_name": "Saka",
      "team": "ARS",
      "position": "MID",
      "now_cost": 10,
      "xpts_next": 0,
      "captain_xpts": 0,
      "fdr": 3,
      "ownership": null,
      "news": "",
      "news_status": "AVAILABLE",
      "price_change_flag": "none",
      "is_starting": true,
      "is_captain": false,
      "is_vice": false
    },
    {
      "id": 9,
      "web_name": "Thiago",
      "team": "BRE",
      "position": "FWD",
      "now_cost": 7.2,
      "xpts_next": 0,
      "captain_xpts": 0,
      "fdr": 3,
      "ownership": null,
      "news": "",
      "news_status": "AVAILABLE",
      "price_change_flag": "none",
      "is_starting": true,
      "is_captain": false,
      "is_vice": false
    },
    {
      "id": 10,
      "web_name": "Bowen",
      "team": "WHU",
      "position": "FWD",
      "now_cost": 7.8,
      "xpts_next": 0,
      "captain_xpts": 0,
      "fdr": 3,
      "ownership": null,
      "news": "",
      "news_status": "AVAILABLE",
      "price_change_flag": "none",
      "is_starting": true,
      "is_captain": true,
      "is_vice": false
    },
    {
      "id": 11,
      "web_name": "Haaland",
      "team": "MCI",
      "position": "FWD",
      "now_cost": 14.7,
      "xpts_next": 0,
      "captain_xpts": 0,
      "fdr": 3,
      "ownership": null,
      "news": "",
      "news_status": "AVAILABLE",
      "price_change_flag": "none",
      "is_starting": true,
      "is_captain": false,
      "is_vice": false
    },
    {
      "id": 12,
      "web_name": "D\u00fabravka",
      "team": "BUR",
      "position": "GK",
      "now_cost": 4,
      "xpts_next": 0,
      "captain_xpts": 0,
      "fdr": 3,
      "ownership": null,
      "news": "",
      "news_status": "AVAILABLE",
      "price_change_flag": "none",
      "is_starting": false,
      "is_captain": false,
      "is_vice": false
    },
    {
      "id": 13,
      "web_name": "O'Reilly",
      "team": "MCI",
      "position": "DEF",
      "now_cost": 5.3,
      "xpts_next": 0,
      "captain_xpts": 0,
      "fdr": 3,
      "ownership": null,
      "news": "",
      "news_status": "AVAILABLE",
      "price_change_flag": "none",
      "is_starting": false,
      "is_captain": false,
      "is_vice": false
    },
    {
      "id": 14,
      "web_name": "Canvot",
      "team": "CRY",
      "position": "DEF",
      "now_cost": 4.5,
      "xpts_next": 0,
      "captain_xpts": 0,
      "fdr": null,
      "ownership": null,
      "news": "",
      "news_status": "AVAILABLE",
      "price_change_flag": "none",
      "is_starting": false,
      "is_captain": false,
      "is_vice": false
    },
    {
      "id": 15,
      "web_name": "Casemiro",
      "team": "MUN",
      "position": "MID",
      "now_cost": 5.8,
      "xpts_next": 0,
      "captain_xpts": 0,
      "fdr": 3,
      "ownership": null,
      "news": "",
      "news_status": "AVAILABLE",
      "price_change_flag": "none",
      "is_starting": false,
      "is_captain": false,
      "is_vice": false
    }
  ],
  "universe": [
    {
      "id": 101,
      "web_name": "Sels",
      "team": "NFO",
      "position": "GK",
      "now_cost": 4.6,
      "xpts_next": 1,
      "captain_xpts": 2,
      "fdr": 3,
      "ownership": null,
      "news": "",
      "news_status": "AVAILABLE",
      "price_change_flag": "none",
      "in_squad": false
    },
    {
      "id": 102,
      "web_name": "Raya",
      "team": "ARS",
      "position": "GK",
      "now_cost": 6.2,
      "xpts_next": 0,
      "captain_xpts": 0,
      "fdr": 3,
      "ownership": null,
      "news": "",
      "news_status": "AVAILABLE",
      "price_change_flag": "none",
      "in_squad": false
    },
    {
      "id": 103,
      "web_name": "Kelleher",
      "team": "BRE",
      "position": "GK",
      "now_cost": 4.8,
      "xpts_next": 0,
      "captain_xpts": 0,
      "fdr": 3,
      "ownership": null,
      "news": "",
      "news_status": "AVAILABLE",
      "price_change_flag": "none",
      "in_squad": false
    },
    {
      "id": 104,
      "web_name": "Roefs",
      "team": "SUN",
      "position": "GK",
      "now_cost": 4.8,
      "xpts_next": 0,
      "captain_xpts": 0,
      "fdr": 3,
      "ownership": null,
      "news": "",
      "news_status": "AVAILABLE",
      "price_change_flag": "none",
      "in_squad": false
    },
    {
      "id": 105,
      "web_name": "Pickford",
      "team": "EVE",
      "position": "GK",
      "now_cost": 5.6,
      "xpts_next": 0,
      "captain_xpts": 0,
      "fdr": 3,
      "ownership": null,
      "news": "",
      "news_status": "AVAILABLE",
      "price_change_flag": "none",
      "in_squad": false
    },
    {
      "id": 106,
      "web_name": "Donnarumma",
      "team": "MCI",
      "position": "GK",
      "now_cost": 5.6,
      "xpts_next": 0,
      "captain_xpts": 0,
      "fdr": 3,
      "ownership": null,
      "news": "",
      "news_status": "AVAILABLE",
      "price_change_flag": "none",
      "in_squad": false
    },
    {
      "id": 107,
      "web_name": "Henderson",
      "team": "CRY",
      "position": "GK",
      "now_cost": 5.1,
      "xpts_next": 0,
      "captain_xpts": 0,
      "fdr": 3,
      "ownership": null,
      "news": "",
      "news_status": "AVAILABLE",
      "price_change_flag": "none",
      "in_squad": false
    },
    {
      "id": 108,
      "web_name": "Verbruggen",
      "team": "BHA",
      "position": "GK",
      "now_cost": 4.6,
      "xpts_next": 0,
      "captain_xpts": 0,
      "fdr": 3,
      "ownership": null,
      "news": "",
      "news_status": "AVAILABLE",
      "price_change_flag": "none",
      "in_squad": true
    },
    {
      "id": 109,
      "web_name": "Petrovi\u0107",
      "team": "BOU",
      "position": "GK",
      "now_cost": 4.6,
      "xpts_next": 0,
      "captain_xpts": 0,
      "fdr": 3,
      "ownership": null,
      "news": "",
      "news_status": "AVAILABLE",
      "price_change_flag": "none",
      "in_squad": false
    },
    {
      "id": 110,
      "web_name": "Leno",
      "team": "FUL",
      "position": "GK",
      "now_cost": 5,
      "xpts_next": 0,
      "captain_xpts": 0,
      "fdr": 3,
      "ownership": null,
      "news": "",
      "news_status": "AVAILABLE",
      "price_change_flag": "none",
      "in_squad": false
    },
    {
      "id": 111,
      "web_name": "Martinez",
      "team": "AVL",
      "position": "GK",
      "now_cost": 5,
      "xpts_next": 0,
      "captain_xpts": 0,
      "fdr": 3,
      "ownership": null,
      "news": "",
      "news_status": "AVAILABLE",
      "price_change_flag": "none",
      "in_squad": false
    },
    {
      "id": 112,
      "web_name": "S\u00e1nchez",
      "team": "CHE",
      "position": "GK",
      "now_cost": 4.8,
      "xpts_next": 0,
      "captain_xpts": 0,
      "fdr": 3,
      "ownership": null,
      "news": "",
      "news_status": "AVAILABLE",
      "price_change_flag": "none",
      "in_squad": false
    },
    {
      "id": 113,
      "web_name": "Lammens",
      "team": "MUN",
      "position": "GK",
      "now_cost": 5.1,
      "xpts_next": 0,
      "captain_xpts": 0,
      "fdr": 3,
      "ownership": null,
      "news": "",
      "news_status": "AVAILABLE",
      "price_change_flag": "none",
      "in_squad": false
    },
    {
      "id": 114,
      "web_name": "D\u00fabravka",
      "team": "BUR",
      "position": "GK",
      "now_cost": 4,
      "xpts_next": 0,
      "captain_xpts": 0,
      "fdr": 3,
      "ownership": null,
      "news": "",
      "news_status": "AVAILABLE",
      "price_change_flag": "none",
      "in_squad": true
    },
    {
      "id": 115,
      "web_name": "Pope",
      "team": "NEW",
      "position": "GK",
      "now_cost": 5,
      "xpts_next": 0,
      "captain_xpts": 0,
      "fdr": 3,
      "ownership": null,
      "news": "",
      "news_status": "AVAILABLE",
      "price_change_flag": "none",
      "in_squad": false
    },
    {
      "id": 116,
      "web_name": "Gabriel",
      "team": "ARS",
      "position": "DEF",
      "now_cost": 7.3,
      "xpts_next": 0,
      "captain_xpts": 0,
      "fdr": 3,
      "ownership": null,
      "news": "",
      "news_status": "AVAILABLE",
      "price_change_flag": "none",
      "in_squad": true
    },
    {
      "id": 117,
      "web_name": "Gu\u00e9hi",
      "team": "MCI",
      "position": "DEF",
      "now_cost": 5.1,
      "xpts_next": 0,
      "captain_xpts": 0,
      "fdr": 3,
      "ownership": null,
      "news": "",
      "news_status": "AVAILABLE",
      "price_change_flag": "none",
      "in_squad": false
    },
    {
      "id": 118,
      "web_name": "Senesi",
      "team": "BOU",
      "position": "DEF",
      "now_cost": 5.2,
      "xpts_next": 0,
      "captain_xpts": 0,
      "fdr": 3,
      "ownership": null,
      "news": "",
      "news_status": "AVAILABLE",
      "price_change_flag": "none",
      "in_squad": false
    },
    {
      "id": 119,
      "web_name": "Virgil",
      "team": "LIV",
      "position": "DEF",
      "now_cost": 6.1,
      "xpts_next": 0,
      "captain_xpts": 0,
      "fdr": 3,
      "ownership": null,
      "news": "",
      "news_status": "AVAILABLE",
      "price_change_flag": "none",
      "in_squad": false
    },
    {
      "id": 120,
      "web_name": "Tarkowski",
      "team": "EVE",
      "position": "DEF",
      "now_cost": 5.8,
      "xpts_next": 0,
      "captain_xpts": 0,
      "fdr": 3,
      "ownership": null,
      "news": "",
      "news_status": "AVAILABLE",
      "price_change_flag": "none",
      "in_squad": false
    },
    {
      "id": 121,
      "web_name": "Truffert",
      "team": "BOU",
      "position": "DEF",
      "now_cost": 4.8,
      "xpts_next": 0,
      "captain_xpts": 0,
      "fdr": 3,
      "ownership": null,
      "news": "",
      "news_status": "AVAILABLE",
      "price_change_flag": "none",
      "in_squad": false
    },
    {
      "id": 122,
      "web_name": "O'Reilly",
      "team": "MCI",
      "position": "DEF",
      "now_cost": 5.3,
      "xpts_next": 0,
      "captain_xpts": 0,
      "fdr": 3,
      "ownership": null,
      "news": "",
      "news_status": "AVAILABLE",
      "price_change_flag": "none",
      "in_squad": true
    },
    {
      "id": 123,
      "web_name": "Lacroix",
      "team": "CRY",
      "position": "DEF",
      "now_cost": 5.2,
      "xpts_next": 0,
      "captain_xpts": 0,
      "fdr": 3,
      "ownership": null,
      "news": "",
      "news_status": "AVAILABLE",
      "price_change_flag": "none",
      "in_squad": false
    },
    {
      "id": 124,
      "web_name": "Matheus N.",
      "team": "MCI",
      "position": "DEF",
      "now_cost": 5.3,
      "xpts_next": 0,
      "captain_xpts": 0,
      "fdr": 3,
      "ownership": null,
      "news": "",
      "news_status": "AVAILABLE",
      "price_change_flag": "none",
      "in_squad": false
    },
    {
      "id": 125,
      "web_name": "Mukiele",
      "team": "SUN",
      "position": "DEF",
      "now_cost": 4.6,
      "xpts_next": 0,
      "captain_xpts": 0,
      "fdr": 3,
      "ownership": null,
      "news": "",
      "news_status": "AVAILABLE",
      "price_change_flag": "none",
      "in_squad": false
    },
    {
      "id": 126,
      "web_name": "J.Timber",
      "team": "ARS",
      "position": "DEF",
      "now_cost": 6,
      "xpts_next": 0,
      "captain_xpts": 0,
      "fdr": 3,
      "ownership": null,
      "news": "",
      "news_status": "AVAILABLE",
      "price_change_flag": "none",
      "in_squad": false
    },
    {
      "id": 127,
      "web_name": "Van Hecke",
      "team": "BHA",
      "position": "DEF",
      "now_cost": 4.7,
      "xpts_next": 0,
      "captain_xpts": 0,
      "fdr": 3,
      "ownership": null,
      "news": "",
      "news_status": "AVAILABLE",
      "price_change_flag": "none",
      "in_squad": false
    },
    {
      "id": 128,
      "web_name": "Saliba",
      "team": "ARS",
      "position": "DEF",
      "now_cost": 6.3,
      "xpts_next": 0,
      "captain_xpts": 0,
      "fdr": 3,
      "ownership": null,
      "news": "",
      "news_status": "AVAILABLE",
      "price_change_flag": "none",
      "in_squad": false
    },
    {
      "id": 129,
      "web_name": "Chalobah",
      "team": "CHE",
      "position": "DEF",
      "now_cost": 5.4,
      "xpts_next": 0,
      "captain_xpts": 0,
      "fdr": 3,
      "ownership": null,
      "news": "",
      "news_status": "AVAILABLE",
      "price_change_flag": "none",
      "in_squad": false
    },
    {
      "id": 130,
      "web_name": "Mu\u00f1oz",
      "team": "CRY",
      "position": "DEF",
      "now_cost": 5.9,
      "xpts_next": 0,
      "captain_xpts": 0,
      "fdr": 3,
      "ownership": null,
      "news": "",
      "news_status": "AVAILABLE",
      "price_change_flag": "none",
      "in_squad": false
    },
    {
      "id": 131,
      "web_name": "Mitchell",
      "team": "CRY",
      "position": "DEF",
      "now_cost": 5,
      "xpts_next": 0,
      "captain_xpts": 0,
      "fdr": 3,
      "ownership": null,
      "news": "",
      "news_status": "AVAILABLE",
      "price_change_flag": "none",
      "in_squad": false
    },
    {
      "id": 132,
      "web_name": "Keane",
      "team": "EVE",
      "position": "DEF",
      "now_cost": 4.5,
      "xpts_next": 0,
      "captain_xpts": 0,
      "fdr": 3,
      "ownership": null,
      "news": "",
      "news_status": "AVAILABLE",
      "price_change_flag": "none",
      "in_squad": false
    },
    {
      "id": 133,
      "web_name": "Collins",
      "team": "BRE",
      "position": "DEF",
      "now_cost": 4.9,
      "xpts_next": 0,
      "captain_xpts": 0,
      "fdr": 3,
      "ownership": null,
      "news": "",
      "news_status": "AVAILABLE",
      "price_change_flag": "none",
      "in_squad": false
    },
    {
      "id": 134,
      "web_name": "Konat\u00e9",
      "team": "LIV",
      "position": "DEF",
      "now_cost": 5.4,
      "xpts_next": 0,
      "captain_xpts": 0,
      "fdr": 3,
      "ownership": null,
      "news": "",
      "news_status": "AVAILABLE",
      "price_change_flag": "none",
      "in_squad": false
    },
    {
      "id": 135,
      "web_name": "Richards",
      "team": "CRY",
      "position": "DEF",
      "now_cost": 4.4,
      "xpts_next": 0,
      "captain_xpts": 0,
      "fdr": 3,
      "ownership": null,
      "news": "Ankle injury - Expected back 01 Jun",
      "news_status": "INJURED",
      "price_change_flag": "none",
      "in_squad": false
    },
    {
      "id": 136,
      "web_name": "N.Williams",
      "team": "NFO",
      "position": "DEF",
      "now_cost": 4.8,
      "xpts_next": 0,
      "captain_xpts": 0,
      "fdr": 3,
      "ownership": null,
      "news": "",
      "news_status": "AVAILABLE",
      "price_change_flag": "none",
      "in_squad": false
    },
    {
      "id": 137,
      "web_name": "Thiaw",
      "team": "NEW",
      "position": "DEF",
      "now_cost": 4.9,
      "xpts_next": 0,
      "captain_xpts": 0,
      "fdr": 3,
      "ownership": null,
      "news": "",
      "news_status": "AVAILABLE",
      "price_change_flag": "none",
      "in_squad": true
    },
    {
      "id": 138,
      "web_name": "Alderete",
      "team": "SUN",
      "position": "DEF",
      "now_cost": 4.1,
      "xpts_next": 0,
      "captain_xpts": 0,
      "fdr": 3,
      "ownership": null,
      "news": "",
      "news_status": "AVAILABLE",
      "price_change_flag": "none",
      "in_squad": false
    },
    {
      "id": 139,
      "web_name": "Andersen",
      "team": "FUL",
      "position": "DEF",
      "now_cost": 4.4,
      "xpts_next": 0,
      "captain_xpts": 0,
      "fdr": 3,
      "ownership": null,
      "news": "",
      "news_status": "AVAILABLE",
      "price_change_flag": "none",
      "in_squad": false
    },
    {
      "id": 140,
      "web_name": "Mavropanos",
      "team": "WHU",
      "position": "DEF",
      "now_cost": 4.5,
      "xpts_next": 0,
      "captain_xpts": 0,
      "fdr": 3,
      "ownership": null,
      "news": "",
      "news_status": "AVAILABLE",
      "price_change_flag": "none",
      "in_squad": false
    },
    {
      "id": 141,
      "web_name": "Milenkovi\u0107",
      "team": "NFO",
      "position": "DEF",
      "now_cost": 5.1,
      "xpts_next": 0,
      "captain_xpts": 0,
      "fdr": 3,
      "ownership": null,
      "news": "",
      "news_status": "AVAILABLE",
      "price_change_flag": "none",
      "in_squad": false
    },
    {
      "id": 142,
      "web_name": "F.Kad\u0131o\u011flu",
      "team": "BHA",
      "position": "DEF",
      "now_cost": 4.5,
      "xpts_next": 0,
      "captain_xpts": 0,
      "fdr": 3,
      "ownership": null,
      "news": "",
      "news_status": "AVAILABLE",
      "price_change_flag": "none",
      "in_squad": false
    },
    {
      "id": 143,
      "web_name": "Cash",
      "team": "AVL",
      "position": "DEF",
      "now_cost": 4.6,
      "xpts_next": 0,
      "captain_xpts": 0,
      "fdr": 3,
      "ownership": null,
      "news": "",
      "news_status": "AVAILABLE",
      "price_change_flag": "none",
      "in_squad": false
    },
    {
      "id": 144,
      "web_name": "Pedro Porro",
      "team": "TOT",
      "position": "DEF",
      "now_cost": 5.2,
      "xpts_next": 0,
      "captain_xpts": 0,
      "fdr": 3,
      "ownership": null,
      "news": "",
      "news_status": "AVAILABLE",
      "price_change_flag": "none",
      "in_squad": false
    },
    {
      "id": 145,
      "web_name": "O'Brien",
      "team": "EVE",
      "position": "DEF",
      "now_cost": 4.9,
      "xpts_next": 0,
      "captain_xpts": 0,
      "fdr": 3,
      "ownership": null,
      "news": "",
      "news_status": "AVAILABLE",
      "price_change_flag": "none",
      "in_squad": false
    },
    {
      "id": 146,
      "web_name": "Ballard",
      "team": "SUN",
      "position": "DEF",
      "now_cost": 4.6,
      "xpts_next": 0,
      "captain_xpts": 0,
      "fdr": 3,
      "ownership": null,
      "news": "",
      "news_status": "AVAILABLE",
      "price_change_flag": "none",
      "in_squad": false
    },
    {
      "id": 147,
      "web_name": "Van de Ven",
      "team": "TOT",
      "position": "DEF",
      "now_cost": 4.4,
      "xpts_next": 0,
      "captain_xpts": 0,
      "fdr": 3,
      "ownership": null,
      "news": "",
      "news_status": "AVAILABLE",
      "price_change_flag": "none",
      "in_squad": false
    },
    {
      "id": 148,
      "web_name": "Lewis-Potter",
      "team": "BRE",
      "position": "DEF",
      "now_cost": 4.8,
      "xpts_next": 0,
      "captain_xpts": 0,
      "fdr": 3,
      "ownership": null,
      "news": "",
      "news_status": "AVAILABLE",
      "price_change_flag": "none",
      "in_squad": false
    },
    {
      "id": 149,
      "web_name": "James",
      "team": "CHE",
      "position": "DEF",
      "now_cost": 5.6,
      "xpts_next": 0,
      "captain_xpts": 0,
      "fdr": 3,
      "ownership": null,
      "news": "",
      "news_status": "AVAILABLE",
      "price_change_flag": "none",
      "in_squad": false
    },
    {
      "id": 150,
      "web_name": "Kayode",
      "team": "BRE",
      "position": "DEF",
      "now_cost": 4.6,
      "xpts_next": 0,
      "captain_xpts": 0,
      "fdr": 3,
      "ownership": null,
      "news": "",
      "news_status": "AVAILABLE",
      "price_change_flag": "none",
      "in_squad": false
    },
    {
      "id": 151,
      "web_name": "Van den Berg",
      "team": "BRE",
      "position": "DEF",
      "now_cost": 4.4,
      "xpts_next": 0,
      "captain_xpts": 0,
      "fdr": 3,
      "ownership": null,
      "news": "",
      "news_status": "AVAILABLE",
      "price_change_flag": "none",
      "in_squad": false
    },
    {
      "id": 152,
      "web_name": "R\u00faben",
      "team": "MCI",
      "position": "DEF",
      "now_cost": 5.5,
      "xpts_next": 0,
      "captain_xpts": 0,
      "fdr": 3,
      "ownership": null,
      "news": "",
      "news_status": "AVAILABLE",
      "price_change_flag": "none",
      "in_squad": false
    },
    {
      "id": 153,
      "web_name": "Shaw",
      "team": "MUN",
      "position": "DEF",
      "now_cost": 4.5,
      "xpts_next": 0,
      "captain_xpts": 0,
      "fdr": 3,
      "ownership": null,
      "news": "",
      "news_status": "AVAILABLE",
      "price_change_flag": "none",
      "in_squad": false
    },
    {
      "id": 154,
      "web_name": "Dalot",
      "team": "MUN",
      "position": "DEF",
      "now_cost": 4.5,
      "xpts_next": 0,
      "captain_xpts": 0,
      "fdr": 3,
      "ownership": null,
      "news": "",
      "news_status": "AVAILABLE",
      "price_change_flag": "none",
      "in_squad": false
    },
    {
      "id": 155,
      "web_name": "Hill",
      "team": "BOU",
      "position": "DEF",
      "now_cost": 4.2,
      "xpts_next": 0,
      "captain_xpts": 0,
      "fdr": 3,
      "ownership": null,
      "news": "",
      "news_status": "AVAILABLE",
      "price_change_flag": "none",
      "in_squad": true
    },
    {
      "id": 156,
      "web_name": "Hume",
      "team": "SUN",
      "position": "DEF",
      "now_cost": 4.5,
      "xpts_next": 0,
      "captain_xpts": 0,
      "fdr": 3,
      "ownership": null,
      "news": "",
      "news_status": "AVAILABLE",
      "price_change_flag": "none",
      "in_squad": false
    },
    {
      "id": 157,
      "web_name": "Calafiori",
      "team": "ARS",
      "position": "DEF",
      "now_cost": 5.6,
      "xpts_next": 0,
      "captain_xpts": 0,
      "fdr": 3,
      "ownership": null,
      "news": "",
      "news_status": "AVAILABLE",
      "price_change_flag": "none",
      "in_squad": false
    },
    {
      "id": 158,
      "web_name": "Rodon",
      "team": "LEE",
      "position": "DEF",
      "now_cost": 3.9,
      "xpts_next": 0,
      "captain_xpts": 0,
      "fdr": 3,
      "ownership": null,
      "news": "",
      "news_status": "AVAILABLE",
      "price_change_flag": "none",
      "in_squad": false
    },
    {
      "id": 159,
      "web_name": "Struijk",
      "team": "LEE",
      "position": "DEF",
      "now_cost": 4.2,
      "xpts_next": 0,
      "captain_xpts": 0,
      "fdr": 3,
      "ownership": null,
      "news": "",
      "news_status": "AVAILABLE",
      "price_change_flag": "none",
      "in_squad": false
    },
    {
      "id": 160,
      "web_name": "Cucurella",
      "team": "CHE",
      "position": "DEF",
      "now_cost": 6.1,
      "xpts_next": 0,
      "captain_xpts": 0,
      "fdr": 3,
      "ownership": null,
      "news": "",
      "news_status": "AVAILABLE",
      "price_change_flag": "none",
      "in_squad": false
    },
    {
      "id": 161,
      "web_name": "Diouf",
      "team": "WHU",
      "position": "DEF",
      "now_cost": 4.1,
      "xpts_next": 0,
      "captain_xpts": 0,
      "fdr": 3,
      "ownership": null,
      "news": "",
      "news_status": "AVAILABLE",
      "price_change_flag": "none",
      "in_squad": false
    },
    {
      "id": 162,
      "web_name": "Bassey",
      "team": "FUL",
      "position": "DEF",
      "now_cost": 4.4,
      "xpts_next": 0,
      "captain_xpts": 0,
      "fdr": 3,
      "ownership": null,
      "news": "",
      "news_status": "AVAILABLE",
      "price_change_flag": "none",
      "in_squad": false
    },
    {
      "id": 163,
      "web_name": "Konsa",
      "team": "AVL",
      "position": "DEF",
      "now_cost": 4.4,
      "xpts_next": 0,
      "captain_xpts": 0,
      "fdr": 3,
      "ownership": null,
      "news": "",
      "news_status": "AVAILABLE",
      "price_change_flag": "none",
      "in_squad": false
    },
    {
      "id": 164,
      "web_name": "Dunk",
      "team": "BHA",
      "position": "DEF",
      "now_cost": 4.5,
      "xpts_next": 0,
      "captain_xpts": 0,
      "fdr": 3,
      "ownership": null,
      "news": "",
      "news_status": "AVAILABLE",
      "price_change_flag": "none",
      "in_squad": false
    },
    {
      "id": 165,
      "web_name": "Bijol",
      "team": "LEE",
      "position": "DEF",
      "now_cost": 3.9,
      "xpts_next": 0,
      "captain_xpts": 0,
      "fdr": 3,
      "ownership": null,
      "news": "",
      "news_status": "AVAILABLE",
      "price_change_flag": "none",
      "in_squad": false
    },
    {
      "id": 166,
      "web_name": "B.Fernandes",
      "team": "MUN",
      "position": "MID",
      "now_cost": 10.4,
      "xpts_next": 0,
      "captain_xpts": 0,
      "fdr": 3,
      "ownership": null,
      "news": "",
      "news_status": "AVAILABLE",
      "price_change_flag": "none",
      "in_squad": true
    },
    {
      "id": 167,
      "web_name": "Semenyo",
      "team": "MCI",
      "position": "MID",
      "now_cost": 8,
      "xpts_next": 0,
      "captain_xpts": 0,
      "fdr": 3,
      "ownership": null,
      "news": "",
      "news_status": "AVAILABLE",
      "price_change_flag": "none",
      "in_squad": false
    },
    {
      "id": 168,
      "web_name": "Gibbs-White",
      "team": "NFO",
      "position": "MID",
      "now_cost": 7.6,
      "xpts_next": 0,
      "captain_xpts": 0,
      "fdr": 3,
      "ownership": null,
      "news": "",
      "news_status": "AVAILABLE",
      "price_change_flag": "none",
      "in_squad": false
    },
    {
      "id": 169,
      "web_name": "Rice",
      "team": "ARS",
      "position": "MID",
      "now_cost": 7.2,
      "xpts_next": 0,
      "captain_xpts": 0,
      "fdr": 3,
      "ownership": null,
      "news": "",
      "news_status": "AVAILABLE",
      "price_change_flag": "none",
      "in_squad": true
    },
    {
      "id": 170,
      "web_name": "Anderson",
      "team": "NFO",
      "position": "MID",
      "now_cost": 5.7,
      "xpts_next": 0,
      "captain_xpts": 0,
      "fdr": 3,
      "ownership": null,
      "news": "",
      "news_status": "AVAILABLE",
      "price_change_flag": "none",
      "in_squad": true
    },
    {
      "id": 171,
      "web_name": "Rogers",
      "team": "AVL",
      "position": "MID",
      "now_cost": 7.3,
      "xpts_next": 0,
      "captain_xpts": 0,
      "fdr": 3,
      "ownership": null,
      "news": "",
      "news_status": "AVAILABLE",
      "price_change_flag": "none",
      "in_squad": false
    },
    {
      "id": 172,
      "web_name": "Wilson",
      "team": "FUL",
      "position": "MID",
      "now_cost": 5.8,
      "xpts_next": 0,
      "captain_xpts": 0,
      "fdr": 3,
      "ownership": null,
      "news": "",
      "news_status": "AVAILABLE",
      "price_change_flag": "none",
      "in_squad": false
    },
    {
      "id": 173,
      "web_name": "Casemiro",
      "team": "MUN",
      "position": "MID",
      "now_cost": 5.8,
      "xpts_next": 0,
      "captain_xpts": 0,
      "fdr": 3,
      "ownership": null,
      "news": "",
      "news_status": "AVAILABLE",
      "price_change_flag": "none",
      "in_squad": true
    },
    {
      "id": 174,
      "web_name": "Szoboszlai",
      "team": "LIV",
      "position": "MID",
      "now_cost": 7.1,
      "xpts_next": 0,
      "captain_xpts": 0,
      "fdr": 3,
      "ownership": null,
      "news": "",
      "news_status": "AVAILABLE",
      "price_change_flag": "none",
      "in_squad": false
    },
    {
      "id": 175,
      "web_name": "Garner",
      "team": "EVE",
      "position": "MID",
      "now_cost": 5.2,
      "xpts_next": 0,
      "captain_xpts": 0,
      "fdr": 3,
      "ownership": null,
      "news": "",
      "news_status": "AVAILABLE",
      "price_change_flag": "none",
      "in_squad": false
    },
    {
      "id": 176,
      "web_name": "Saka",
      "team": "ARS",
      "position": "MID",
      "now_cost": 10,
      "xpts_next": 0,
      "captain_xpts": 0,
      "fdr": 3,
      "ownership": null,
      "news": "",
      "news_status": "AVAILABLE",
      "price_change_flag": "none",
      "in_squad": true
    },
    {
      "id": 177,
      "web_name": "Enzo",
      "team": "CHE",
      "position": "MID",
      "now_cost": 6.5,
      "xpts_next": 0,
      "captain_xpts": 0,
      "fdr": 3,
      "ownership": null,
      "news": "",
      "news_status": "AVAILABLE",
      "price_change_flag": "none",
      "in_squad": false
    },
    {
      "id": 178,
      "web_name": "Bruno G.",
      "team": "NEW",
      "position": "MID",
      "now_cost": 6.9,
      "xpts_next": 0,
      "captain_xpts": 0,
      "fdr": 3,
      "ownership": null,
      "news": "",
      "news_status": "AVAILABLE",
      "price_change_flag": "none",
      "in_squad": false
    },
    {
      "id": 179,
      "web_name": "Dewsbury-Hall",
      "team": "EVE",
      "position": "MID",
      "now_cost": 5.3,
      "xpts_next": 0,
      "captain_xpts": 0,
      "fdr": 3,
      "ownership": null,
      "news": "",
      "news_status": "AVAILABLE",
      "price_change_flag": "none",
      "in_squad": false
    },
    {
      "id": 180,
      "web_name": "Mbeumo",
      "team": "MUN",
      "position": "MID",
      "now_cost": 8.3,
      "xpts_next": 0,
      "captain_xpts": 0,
      "fdr": 3,
      "ownership": null,
      "news": "",
      "news_status": "AVAILABLE",
      "price_change_flag": "none",
      "in_squad": false
    },
    {
      "id": 181,
      "web_name": "E.Le F\u00e9e",
      "team": "SUN",
      "position": "MID",
      "now_cost": 4.8,
      "xpts_next": 0,
      "captain_xpts": 0,
      "fdr": 3,
      "ownership": null,
      "news": "",
      "news_status": "AVAILABLE",
      "price_change_flag": "none",
      "in_squad": false
    },
    {
      "id": 182,
      "web_name": "Gravenberch",
      "team": "LIV",
      "position": "MID",
      "now_cost": 5.4,
      "xpts_next": 0,
      "captain_xpts": 0,
      "fdr": 3,
      "ownership": null,
      "news": "",
      "news_status": "AVAILABLE",
      "price_change_flag": "none",
      "in_squad": false
    },
    {
      "id": 183,
      "web_name": "Cunha",
      "team": "MUN",
      "position": "MID",
      "now_cost": 8.1,
      "xpts_next": 0,
      "captain_xpts": 0,
      "fdr": 3,
      "ownership": null,
      "news": "",
      "news_status": "AVAILABLE",
      "price_change_flag": "none",
      "in_squad": false
    },
    {
      "id": 184,
      "web_name": "Tavernier",
      "team": "BOU",
      "position": "MID",
      "now_cost": 5.3,
      "xpts_next": 0,
      "captain_xpts": 0,
      "fdr": 3,
      "ownership": null,
      "news": "",
      "news_status": "AVAILABLE",
      "price_change_flag": "none",
      "in_squad": false
    },
    {
      "id": 185,
      "web_name": "Stach",
      "team": "LEE",
      "position": "MID",
      "now_cost": 4.8,
      "xpts_next": 0,
      "captain_xpts": 0,
      "fdr": 3,
      "ownership": null,
      "news": "Ankle injury - Expected back 01 Jun",
      "news_status": "INJURED",
      "price_change_flag": "none",
      "in_squad": false
    },
    {
      "id": 186,
      "web_name": "Scott",
      "team": "BOU",
      "position": "MID",
      "now_cost": 4.9,
      "xpts_next": 0,
      "captain_xpts": 0,
      "fdr": 3,
      "ownership": null,
      "news": "",
      "news_status": "AVAILABLE",
      "price_change_flag": "none",
      "in_squad": false
    },
    {
      "id": 187,
      "web_name": "O.Dango",
      "team": "BRE",
      "position": "MID",
      "now_cost": 5.6,
      "xpts_next": 0,
      "captain_xpts": 0,
      "fdr": 3,
      "ownership": null,
      "news": "",
      "news_status": "AVAILABLE",
      "price_change_flag": "none",
      "in_squad": false
    },
    {
      "id": 188,
      "web_name": "Cherki",
      "team": "MCI",
      "position": "MID",
      "now_cost": 6.5,
      "xpts_next": 0,
      "captain_xpts": 0,
      "fdr": 3,
      "ownership": null,
      "news": "",
      "news_status": "AVAILABLE",
      "price_change_flag": "none",
      "in_squad": false
    },
    {
      "id": 189,
      "web_name": "M.Fernandes",
      "team": "WHU",
      "position": "MID",
      "now_cost": 5.5,
      "xpts_next": 0,
      "captain_xpts": 0,
      "fdr": 3,
      "ownership": null,
      "news": "",
      "news_status": "AVAILABLE",
      "price_change_flag": "none",
      "in_squad": false
    },
    {
      "id": 190,
      "web_name": "Ampadu",
      "team": "LEE",
      "position": "MID",
      "now_cost": 4.9,
      "xpts_next": 0,
      "captain_xpts": 0,
      "fdr": 3,
      "ownership": null,
      "news": "",
      "news_status": "AVAILABLE",
      "price_change_flag": "none",
      "in_squad": false
    },
    {
      "id": 191,
      "web_name": "Zubimendi",
      "team": "ARS",
      "position": "MID",
      "now_cost": 4.9,
      "xpts_next": 0,
      "captain_xpts": 0,
      "fdr": 3,
      "ownership": null,
      "news": "",
      "news_status": "AVAILABLE",
      "price_change_flag": "none",
      "in_squad": false
    },
    {
      "id": 192,
      "web_name": "Gakpo",
      "team": "LIV",
      "position": "MID",
      "now_cost": 7.3,
      "xpts_next": 0,
      "captain_xpts": 0,
      "fdr": 3,
      "ownership": null,
      "news": "",
      "news_status": "AVAILABLE",
      "price_change_flag": "none",
      "in_squad": false
    },
    {
      "id": 193,
      "web_name": "Foden",
      "team": "MCI",
      "position": "MID",
      "now_cost": 8,
      "xpts_next": 0,
      "captain_xpts": 0,
      "fdr": 3,
      "ownership": null,
      "news": "",
      "news_status": "AVAILABLE",
      "price_change_flag": "none",
      "in_squad": false
    },
    {
      "id": 194,
      "web_name": "Ndiaye",
      "team": "EVE",
      "position": "MID",
      "now_cost": 6.3,
      "xpts_next": 0,
      "captain_xpts": 0,
      "fdr": 3,
      "ownership": null,
      "news": "",
      "news_status": "AVAILABLE",
      "price_change_flag": "none",
      "in_squad": false
    },
    {
      "id": 195,
      "web_name": "Anthony",
      "team": "BUR",
      "position": "MID",
      "now_cost": 5,
      "xpts_next": 0,
      "captain_xpts": 0,
      "fdr": 3,
      "ownership": null,
      "news": "",
      "news_status": "AVAILABLE",
      "price_change_flag": "none",
      "in_squad": false
    },
    {
      "id": 196,
      "web_name": "Aaronson",
      "team": "LEE",
      "position": "MID",
      "now_cost": 5.4,
      "xpts_next": 0,
      "captain_xpts": 0,
      "fdr": 3,
      "ownership": null,
      "news": "",
      "news_status": "AVAILABLE",
      "price_change_flag": "none",
      "in_squad": false
    },
    {
      "id": 197,
      "web_name": "J.Palhinha",
      "team": "TOT",
      "position": "MID",
      "now_cost": 5.5,
      "xpts_next": 0,
      "captain_xpts": 0,
      "fdr": 3,
      "ownership": null,
      "news": "",
      "news_status": "AVAILABLE",
      "price_change_flag": "none",
      "in_squad": false
    },
    {
      "id": 198,
      "web_name": "Schade",
      "team": "BRE",
      "position": "MID",
      "now_cost": 6.8,
      "xpts_next": 0,
      "captain_xpts": 0,
      "fdr": 3,
      "ownership": null,
      "news": "",
      "news_status": "AVAILABLE",
      "price_change_flag": "none",
      "in_squad": false
    },
    {
      "id": 199,
      "web_name": "Neto",
      "team": "CHE",
      "position": "MID",
      "now_cost": 7,
      "xpts_next": 0,
      "captain_xpts": 0,
      "fdr": 3,
      "ownership": null,
      "news": "",
      "news_status": "AVAILABLE",
      "price_change_flag": "none",
      "in_squad": false
    },
    {
      "id": 200,
      "web_name": "Wirtz",
      "team": "LIV",
      "position": "MID",
      "now_cost": 8.3,
      "xpts_next": 0,
      "captain_xpts": 0,
      "fdr": 3,
      "ownership": null,
      "news": "",
      "news_status": "AVAILABLE",
      "price_change_flag": "none",
      "in_squad": false
    },
    {
      "id": 201,
      "web_name": "Xhaka",
      "team": "SUN",
      "position": "MID",
      "now_cost": 5.1,
      "xpts_next": 0,
      "captain_xpts": 0,
      "fdr": 3,
      "ownership": null,
      "news": "",
      "news_status": "AVAILABLE",
      "price_change_flag": "none",
      "in_squad": false
    },
    {
      "id": 202,
      "web_name": "M.Salah",
      "team": "LIV",
      "position": "MID",
      "now_cost": 14,
      "xpts_next": 0,
      "captain_xpts": 0,
      "fdr": 3,
      "ownership": null,
      "news": "",
      "news_status": "AVAILABLE",
      "price_change_flag": "none",
      "in_squad": false
    },
    {
      "id": 203,
      "web_name": "Doku",
      "team": "MCI",
      "position": "MID",
      "now_cost": 6.5,
      "xpts_next": 0,
      "captain_xpts": 0,
      "fdr": 3,
      "ownership": null,
      "news": "",
      "news_status": "AVAILABLE",
      "price_change_flag": "none",
      "in_squad": false
    },
    {
      "id": 204,
      "web_name": "Trossard",
      "team": "ARS",
      "position": "MID",
      "now_cost": 6.6,
      "xpts_next": 0,
      "captain_xpts": 0,
      "fdr": 3,
      "ownership": null,
      "news": "",
      "news_status": "AVAILABLE",
      "price_change_flag": "none",
      "in_squad": false
    },
    {
      "id": 205,
      "web_name": "Minteh",
      "team": "BHA",
      "position": "MID",
      "now_cost": 5.5,
      "xpts_next": 0,
      "captain_xpts": 0,
      "fdr": 3,
      "ownership": null,
      "news": "",
      "news_status": "AVAILABLE",
      "price_change_flag": "none",
      "in_squad": false
    },
    {
      "id": 206,
      "web_name": "Sarr",
      "team": "CRY",
      "position": "MID",
      "now_cost": 6.4,
      "xpts_next": 0,
      "captain_xpts": 0,
      "fdr": 3,
      "ownership": null,
      "news": "",
      "news_status": "AVAILABLE",
      "price_change_flag": "none",
      "in_squad": false
    },
    {
      "id": 207,
      "web_name": "Palmer",
      "team": "CHE",
      "position": "MID",
      "now_cost": 10.3,
      "xpts_next": 0,
      "captain_xpts": 0,
      "fdr": 3,
      "ownership": null,
      "news": "",
      "news_status": "AVAILABLE",
      "price_change_flag": "none",
      "in_squad": false
    },
    {
      "id": 208,
      "web_name": "Eze",
      "team": "ARS",
      "position": "MID",
      "now_cost": 7.3,
      "xpts_next": 0,
      "captain_xpts": 0,
      "fdr": 3,
      "ownership": null,
      "news": "",
      "news_status": "AVAILABLE",
      "price_change_flag": "none",
      "in_squad": false
    },
    {
      "id": 209,
      "web_name": "Damsgaard",
      "team": "BRE",
      "position": "MID",
      "now_cost": 5.6,
      "xpts_next": 0,
      "captain_xpts": 0,
      "fdr": 3,
      "ownership": null,
      "news": "",
      "news_status": "AVAILABLE",
      "price_change_flag": "none",
      "in_squad": false
    },
    {
      "id": 210,
      "web_name": "Wharton",
      "team": "CRY",
      "position": "MID",
      "now_cost": 5,
      "xpts_next": 0,
      "captain_xpts": 0,
      "fdr": 3,
      "ownership": null,
      "news": "",
      "news_status": "AVAILABLE",
      "price_change_flag": "none",
      "in_squad": false
    },
    {
      "id": 211,
      "web_name": "Caicedo",
      "team": "CHE",
      "position": "MID",
      "now_cost": 5.7,
      "xpts_next": 0,
      "captain_xpts": 0,
      "fdr": 3,
      "ownership": null,
      "news": "",
      "news_status": "AVAILABLE",
      "price_change_flag": "none",
      "in_squad": false
    },
    {
      "id": 212,
      "web_name": "Summerville",
      "team": "WHU",
      "position": "MID",
      "now_cost": 5.4,
      "xpts_next": 0,
      "captain_xpts": 0,
      "fdr": 3,
      "ownership": null,
      "news": "",
      "news_status": "AVAILABLE",
      "price_change_flag": "none",
      "in_squad": false
    },
    {
      "id": 213,
      "web_name": "Okafor",
      "team": "LEE",
      "position": "MID",
      "now_cost": 5.5,
      "xpts_next": 0,
      "captain_xpts": 0,
      "fdr": 3,
      "ownership": null,
      "news": "Calf injury - Expected back 01 Jun",
      "news_status": "INJURED",
      "price_change_flag": "none",
      "in_squad": false
    },
    {
      "id": 214,
      "web_name": "Mac Allister",
      "team": "LIV",
      "position": "MID",
      "now_cost": 6.1,
      "xpts_next": 0,
      "captain_xpts": 0,
      "fdr": 3,
      "ownership": null,
      "news": "",
      "news_status": "AVAILABLE",
      "price_change_flag": "none",
      "in_squad": false
    },
    {
      "id": 215,
      "web_name": "J.Gomes",
      "team": "WOL",
      "position": "MID",
      "now_cost": 5.3,
      "xpts_next": 0,
      "captain_xpts": 0,
      "fdr": 3,
      "ownership": null,
      "news": "",
      "news_status": "AVAILABLE",
      "price_change_flag": "none",
      "in_squad": false
    },
    {
      "id": 216,
      "web_name": "Barnes",
      "team": "NEW",
      "position": "MID",
      "now_cost": 6.1,
      "xpts_next": 0,
      "captain_xpts": 0,
      "fdr": 3,
      "ownership": null,
      "news": "",
      "news_status": "AVAILABLE",
      "price_change_flag": "none",
      "in_squad": false
    },
    {
      "id": 217,
      "web_name": "Yarmoliuk",
      "team": "BRE",
      "position": "MID",
      "now_cost": 5,
      "xpts_next": 0,
      "captain_xpts": 0,
      "fdr": 3,
      "ownership": null,
      "news": "",
      "news_status": "AVAILABLE",
      "price_change_flag": "none",
      "in_squad": false
    },
    {
      "id": 218,
      "web_name": "McGinn",
      "team": "AVL",
      "position": "MID",
      "now_cost": 5.3,
      "xpts_next": 0,
      "captain_xpts": 0,
      "fdr": 3,
      "ownership": null,
      "news": "",
      "news_status": "AVAILABLE",
      "price_change_flag": "none",
      "in_squad": false
    },
    {
      "id": 219,
      "web_name": "Iwobi",
      "team": "FUL",
      "position": "MID",
      "now_cost": 6.1,
      "xpts_next": 0,
      "captain_xpts": 0,
      "fdr": 3,
      "ownership": null,
      "news": "",
      "news_status": "AVAILABLE",
      "price_change_flag": "none",
      "in_squad": false
    },
    {
      "id": 220,
      "web_name": "Sou\u010dek",
      "team": "WHU",
      "position": "MID",
      "now_cost": 5.7,
      "xpts_next": 0,
      "captain_xpts": 0,
      "fdr": 3,
      "ownership": null,
      "news": "",
      "news_status": "AVAILABLE",
      "price_change_flag": "none",
      "in_squad": false
    },
    {
      "id": 221,
      "web_name": "Haaland",
      "team": "MCI",
      "position": "FWD",
      "now_cost": 14.7,
      "xpts_next": 0,
      "captain_xpts": 0,
      "fdr": 3,
      "ownership": null,
      "news": "",
      "news_status": "AVAILABLE",
      "price_change_flag": "none",
      "in_squad": true
    },
    {
      "id": 222,
      "web_name": "Bowen",
      "team": "WHU",
      "position": "FWD",
      "now_cost": 7.8,
      "xpts_next": 0,
      "captain_xpts": 0,
      "fdr": 3,
      "ownership": null,
      "news": "",
      "news_status": "AVAILABLE",
      "price_change_flag": "none",
      "in_squad": true
    },
    {
      "id": 223,
      "web_name": "Thiago",
      "team": "BRE",
      "position": "FWD",
      "now_cost": 7.2,
      "xpts_next": 0,
      "captain_xpts": 0,
      "fdr": 3,
      "ownership": null,
      "news": "",
      "news_status": "AVAILABLE",
      "price_change_flag": "none",
      "in_squad": true
    },
    {
      "id": 224,
      "web_name": "Jo\u00e3o Pedro",
      "team": "CHE",
      "position": "FWD",
      "now_cost": 7.4,
      "xpts_next": 0,
      "captain_xpts": 0,
      "fdr": 3,
      "ownership": null,
      "news": "",
      "news_status": "AVAILABLE",
      "price_change_flag": "none",
      "in_squad": false
    },
    {
      "id": 225,
      "web_name": "Watkins",
      "team": "AVL",
      "position": "FWD",
      "now_cost": 8.7,
      "xpts_next": 0,
      "captain_xpts": 0,
      "fdr": 3,
      "ownership": null,
      "news": "",
      "news_status": "AVAILABLE",
      "price_change_flag": "none",
      "in_squad": false
    },
    {
      "id": 226,
      "web_name": "Calvert-Lewin",
      "team": "LEE",
      "position": "FWD",
      "now_cost": 5.8,
      "xpts_next": 0,
      "captain_xpts": 0,
      "fdr": 3,
      "ownership": null,
      "news": "",
      "news_status": "AVAILABLE",
      "price_change_flag": "none",
      "in_squad": false
    },
    {
      "id": 227,
      "web_name": "Gy\u00f6keres",
      "team": "ARS",
      "position": "FWD",
      "now_cost": 9.1,
      "xpts_next": 0,
      "captain_xpts": 0,
      "fdr": 3,
      "ownership": null,
      "news": "",
      "news_status": "AVAILABLE",
      "price_change_flag": "none",
      "in_squad": false
    },
    {
      "id": 228,
      "web_name": "Welbeck",
      "team": "BHA",
      "position": "FWD",
      "now_cost": 6.3,
      "xpts_next": 0,
      "captain_xpts": 0,
      "fdr": 3,
      "ownership": null,
      "news": "",
      "news_status": "AVAILABLE",
      "price_change_flag": "none",
      "in_squad": false
    },
    {
      "id": 229,
      "web_name": "Ekitik\u00e9",
      "team": "LIV",
      "position": "FWD",
      "now_cost": 9,
      "xpts_next": 0,
      "captain_xpts": 0,
      "fdr": 3,
      "ownership": null,
      "news": "Achilles injury - Expected back 01 Jul",
      "news_status": "INJURED",
      "price_change_flag": "none",
      "in_squad": false
    },
    {
      "id": 230,
      "web_name": "Richarlison",
      "team": "TOT",
      "position": "FWD",
      "now_cost": 6.5,
      "xpts_next": 0,
      "captain_xpts": 0,
      "fdr": 3,
      "ownership": null,
      "news": "",
      "news_status": "AVAILABLE",
      "price_change_flag": "none",
      "in_squad": false
    },
    {
      "id": 231,
      "web_name": "Evanilson",
      "team": "BOU",
      "position": "FWD",
      "now_cost": 6.6,
      "xpts_next": 0,
      "captain_xpts": 0,
      "fdr": 3,
      "ownership": null,
      "news": "",
      "news_status": "AVAILABLE",
      "price_change_flag": "none",
      "in_squad": false
    },
    {
      "id": 232,
      "web_name": "Mateta",
      "team": "CRY",
      "position": "FWD",
      "now_cost": 7.6,
      "xpts_next": 0,
      "captain_xpts": 0,
      "fdr": 3,
      "ownership": null,
      "news": "",
      "news_status": "AVAILABLE",
      "price_change_flag": "none",
      "in_squad": false
    },
    {
      "id": 233,
      "web_name": "Igor Jesus",
      "team": "NFO",
      "position": "FWD",
      "now_cost": 5.9,
      "xpts_next": 0,
      "captain_xpts": 0,
      "fdr": 3,
      "ownership": null,
      "news": "",
      "news_status": "AVAILABLE",
      "price_change_flag": "none",
      "in_squad": false
    },
    {
      "id": 234,
      "web_name": "Kroupi.Jr",
      "team": "BOU",
      "position": "FWD",
      "now_cost": 4.7,
      "xpts_next": 0,
      "captain_xpts": 0,
      "fdr": 3,
      "ownership": null,
      "news": "",
      "news_status": "AVAILABLE",
      "price_change_flag": "none",
      "in_squad": false
    },
    {
      "id": 235,
      "web_name": "Ra\u00fal",
      "team": "FUL",
      "position": "FWD",
      "now_cost": 5.9,
      "xpts_next": 0,
      "captain_xpts": 0,
      "fdr": 3,
      "ownership": null,
      "news": "",
      "news_status": "AVAILABLE",
      "price_change_flag": "none",
      "in_squad": false
    },
    {
      "id": 236,
      "web_name": "\u0160e\u0161ko",
      "team": "MUN",
      "position": "FWD",
      "now_cost": 7.2,
      "xpts_next": 0,
      "captain_xpts": 0,
      "fdr": 3,
      "ownership": null,
      "news": "",
      "news_status": "AVAILABLE",
      "price_change_flag": "none",
      "in_squad": false
    },
    {
      "id": 237,
      "web_name": "Woltemade",
      "team": "NEW",
      "position": "FWD",
      "now_cost": 6.7,
      "xpts_next": 0,
      "captain_xpts": 0,
      "fdr": 3,
      "ownership": null,
      "news": "",
      "news_status": "AVAILABLE",
      "price_change_flag": "none",
      "in_squad": false
    },
    {
      "id": 238,
      "web_name": "Beto",
      "team": "EVE",
      "position": "FWD",
      "now_cost": 5.1,
      "xpts_next": 0,
      "captain_xpts": 0,
      "fdr": 3,
      "ownership": null,
      "news": "",
      "news_status": "AVAILABLE",
      "price_change_flag": "none",
      "in_squad": false
    },
    {
      "id": 239,
      "web_name": "Flemming",
      "team": "BUR",
      "position": "FWD",
      "now_cost": 5.3,
      "xpts_next": 0,
      "captain_xpts": 0,
      "fdr": 3,
      "ownership": null,
      "news": "",
      "news_status": "AVAILABLE",
      "price_change_flag": "none",
      "in_squad": false
    },
    {
      "id": 240,
      "web_name": "Barry",
      "team": "EVE",
      "position": "FWD",
      "now_cost": 5.7,
      "xpts_next": 0,
      "captain_xpts": 0,
      "fdr": 3,
      "ownership": null,
      "news": "",
      "news_status": "AVAILABLE",
      "price_change_flag": "none",
      "in_squad": false
    },
    {
      "id": 241,
      "web_name": "Brobbey",
      "team": "SUN",
      "position": "FWD",
      "now_cost": 5.3,
      "xpts_next": 0,
      "captain_xpts": 0,
      "fdr": 3,
      "ownership": null,
      "news": "",
      "news_status": "AVAILABLE",
      "price_change_flag": "none",
      "in_squad": false
    },
    {
      "id": 242,
      "web_name": "Osula",
      "team": "NEW",
      "position": "FWD",
      "now_cost": 5.5,
      "xpts_next": 0,
      "captain_xpts": 0,
      "fdr": 3,
      "ownership": null,
      "news": "",
      "news_status": "AVAILABLE",
      "price_change_flag": "none",
      "in_squad": false
    },
    {
      "id": 243,
      "web_name": "Strand Larsen",
      "team": "CRY",
      "position": "FWD",
      "now_cost": 5.8,
      "xpts_next": 0,
      "captain_xpts": 0,
      "fdr": 3,
      "ownership": null,
      "news": "",
      "news_status": "AVAILABLE",
      "price_change_flag": "none",
      "in_squad": false
    },
    {
      "id": 244,
      "web_name": "Isidor",
      "team": "SUN",
      "position": "FWD",
      "now_cost": 5,
      "xpts_next": 0,
      "captain_xpts": 0,
      "fdr": 3,
      "ownership": null,
      "news": "",
      "news_status": "AVAILABLE",
      "price_change_flag": "none",
      "in_squad": false
    },
    {
      "id": 245,
      "web_name": "Man\u00e9",
      "team": "WOL",
      "position": "FWD",
      "now_cost": 4.2,
      "xpts_next": 0,
      "captain_xpts": 0,
      "fdr": 3,
      "ownership": null,
      "news": "",
      "news_status": "AVAILABLE",
      "price_change_flag": "none",
      "in_squad": false
    },
    {
      "id": 246,
      "web_name": "Nmecha",
      "team": "LEE",
      "position": "FWD",
      "now_cost": 5,
      "xpts_next": 0,
      "captain_xpts": 0,
      "fdr": 3,
      "ownership": null,
      "news": "",
      "news_status": "AVAILABLE",
      "price_change_flag": "none",
      "in_squad": false
    },
    {
      "id": 247,
      "web_name": "Tolu",
      "team": "WOL",
      "position": "FWD",
      "now_cost": 5.1,
      "xpts_next": 0,
      "captain_xpts": 0,
      "fdr": 3,
      "ownership": null,
      "news": "",
      "news_status": "AVAILABLE",
      "price_change_flag": "none",
      "in_squad": false
    },
    {
      "id": 248,
      "web_name": "Taty",
      "team": "WHU",
      "position": "FWD",
      "now_cost": 5.5,
      "xpts_next": 0,
      "captain_xpts": 0,
      "fdr": 3,
      "ownership": null,
      "news": "",
      "news_status": "AVAILABLE",
      "price_change_flag": "none",
      "in_squad": false
    },
    {
      "id": 249,
      "web_name": "Foster",
      "team": "BUR",
      "position": "FWD",
      "now_cost": 4.9,
      "xpts_next": 0,
      "captain_xpts": 0,
      "fdr": 3,
      "ownership": null,
      "news": "",
      "news_status": "AVAILABLE",
      "price_change_flag": "none",
      "in_squad": false
    }
  ]
}